{"mean":{"confidence_interval":{"confidence_level":0.95,"lower_bound":252144.63321640386,"upper_bound":257203.67436637427},"point_estimate":254624.07185588672,"standard_error":1286.8818206176795},"median":{"confidence_interval":{"confidence_level":0.95,"lower_bound":249708.125,"upper_bound":256837.29923569143},"point_estimate":253407.18313022592,"standard_error":1644.5798856335066},"median_abs_dev":{"confidence_interval":{"confidence_level":0.95,"lower_bound":9403.420218519976,"upper_bound":15414.204039335784},"point_estimate":11937.3546824561,"standard_error":1474.89223825336},"slope":{"confidence_interval":{"confidence_level":0.95,"lower_bound":253871.11036844194,"upper_bound":258277.08419963482},"point_estimate":256018.3304115561,"standard_error":1124.5840814332178},"std_dev":{"confidence_interval":{"confidence_level":0.95,"lower_bound":10729.744282063582,"upper_bound":15107.273447852338},"point_estimate":12952.62265459122,"standard_error":1125.734112264896}}