{"mean":{"confidence_interval":{"confidence_level":0.95,"lower_bound":4987.949386748713,"upper_bound":5087.543771495498},"point_estimate":5035.447985993572,"standard_error":25.451365627971736},"median":{"confidence_interval":{"confidence_level":0.95,"lower_bound":4915.31078904992,"upper_bound":4955.580858764166},"point_estimate":4930.3330472921425,"standard_error":12.069940040841848},"median_abs_dev":{"confidence_interval":{"confidence_level":0.95,"lower_bound":89.54273859631904,"upper_bound":142.08690571416784},"point_estimate":113.92757687292489,"standard_error":14.972494746477508},"slope":{"confidence_interval":{"confidence_level":0.95,"lower_bound":4876.151756905892,"upper_bound":4906.772062930373},"point_estimate":4890.405638545684,"standard_error":7.83086127415649},"std_dev":{"confidence_interval":{"confidence_level":0.95,"lower_bound":201.6593421210085,"upper_bound":299.51168755660507},"point_estimate":255.6742455396167,"standard_error":24.93622940556415}}