{"mean":{"confidence_interval":{"confidence_level":0.95,"lower_bound":287390.49283906,"upper_bound":309126.2817082275},"point_estimate":297445.81526162353,"standard_error":5554.245472503722},"median":{"confidence_interval":{"confidence_level":0.95,"lower_bound":272362.27855861245,"upper_bound":282158.79910714284},"point_estimate":277912.97807017545,"standard_error":2918.507734109728},"median_abs_dev":{"confidence_interval":{"confidence_level":0.95,"lower_bound":13428.481628168707,"upper_bound":28107.219892073077},"point_estimate":19453.4451865402,"standard_error":3913.490054513584},"slope":{"confidence_interval":{"confidence_level":0.95,"lower_bound":269563.8263307828,"upper_bound":275284.9902957414},"point_estimate":272201.8525823851,"standard_error":1462.1102010267825},"std_dev":{"confidence_interval":{"confidence_level":0.95,"lower_bound":35326.44300948868,"upper_bound":74201.80383243834},"point_estimate":55908.85524522446,"standard_error":9987.493299632983}}