{"mean":{"confidence_interval":{"confidence_level":0.95,"lower_bound":22145.456323836173,"upper_bound":22342.809963396256},"point_estimate":22240.60696007023,"standard_error":50.46802252156921},"median":{"confidence_interval":{"confidence_level":0.95,"lower_bound":22141.94735134258,"upper_bound":22366.76102458019},"point_estimate":22214.91841587572,"standard_error":45.73846383682556},"median_abs_dev":{"confidence_interval":{"confidence_level":0.95,"lower_bound":26.96174262184556,"upper_bound":286.54161702530615},"point_estimate":85.52990045343141,"standard_error":72.91377208700865},"slope":{"confidence_interval":{"confidence_level":0.95,"lower_bound":22196.31758000289,"upper_bound":22315.75029297789},"point_estimate":22245.29138824184,"standard_error":30.515716779219478},"std_dev":{"confidence_interval":{"confidence_level":0.95,"lower_bound":70.75836175805237,"upper_bound":222.14283208430567},"point_estimate":168.37640238470547,"standard_error":37.95791748070991}}